{
  "data_asset_type": null,
  "expectation_suite_name": "my_suite",
  "expectations": [
    {
      "expectation_type": "expect_table_columns_to_match_ordered_list",
      "kwargs": {
        "column_list": [
          "pet_id",
          "name",
          "pet_type",
          "birth_date",
          "owner"
        ]
      },
      "meta": {
        "notes": {
          "content": "Some clever comment about this expectation. **Markdown** `Supported`",
          "format": "markdown"
        }
      }
    }
  ],
  "ge_cloud_id": null,
  "meta": {
    "great_expectations_version": "0.15.50"
  }
}